adwaith/__init__.py
adwaith/engine.py
adwaith/laws.py
adwaith/adwaith/__init__.py
adwaith/adwaith/engine.py
adwaith/adwaith/laws.py
adwaith-0.1.0.dist-info/licenses/LICENSE
adwaith-0.1.0.dist-info/METADATA
adwaith-0.1.0.dist-info/WHEEL
adwaith-0.1.0.dist-info/top_level.txt
adwaith-0.1.0.dist-info/RECORD
