Metadata-Version: 2.4
Name: adwaith
Version: 0.1.0
Summary: Quantum logic + hacking law + inference engine
Home-page: https://github.com/yourusername/adwaith
Author: Adwaith
Author-email: adwaith2007@gmail.com
License: MIT
Classifier: Programming Language :: Python :: 3
Classifier: Operating System :: OS Independent
Requires-Python: >=3.7
License-File: LICENSE
Dynamic: author
Dynamic: author-email
Dynamic: classifier
Dynamic: description
Dynamic: description-content-type
Dynamic: home-page
Dynamic: license
Dynamic: license-file
Dynamic: requires-python
Dynamic: summary
